[
{
  "model": "protagonists.protagonist",
  "pk": 1,
  "fields": {
    "first_name": "Harry",
    "last_name": "Potter",
    "character_bio": "The Boy Who Lived\r\nThe Boy Who Returned",
    "quote": "I'm a What?",
    "character_archetypes": [
      1,
      19
    ],
    "books": [
      1,
      2,
      3,
      4,
      5,
      6,
      7
    ]
  }
},
{
  "model": "protagonists.protagonist",
  "pk": 6,
  "fields": {
    "first_name": "Monkey D Luffy",
    "last_name": "",
    "character_bio": "A young boy who dreamed of being a pirate. He ate the Gomu-Gomu Devil fruit which turned him in to a 'Rubber Man' and gave him super stretching abilities. All Devil fruit users are unable to swim and lose their powers in the sea. As he makes his way across the Grand Line, the infamous sea of adventure he builds a crew of companions named the 'Straw Hat Pirates', named after the straw hat he wears,  a gift from his childhood idol.",
    "quote": "I'm gonna be king of the pirates!",
    "character_archetypes": [
      1,
      14,
      15,
      16,
      17,
      20,
      44,
      75,
      76
    ],
    "books": [
      42
    ]
  }
},
{
  "model": "protagonists.protagonist",
  "pk": 7,
  "fields": {
    "first_name": "Izuku",
    "last_name": "Midoriya",
    "character_bio": "in a world where everyone has a quirk (a superpower) Midoriya Izuku, a quirkless teenage inherits the quirk of his idol, the number one hero All Might. with this new ability he aims for the top of the hero-led society, as the new symbol of peace",
    "quote": "You're the best. That’s why I want to defeat you!",
    "character_archetypes": [
      1,
      13,
      17,
      20,
      55
    ],
    "books": [
      55
    ]
  }
}
]
